{
    "key_info": {
        "day": 0,
        "money": 1000
    },
    
    "belongings": {
        "axe": [
            1, "wood"
        ],
        "sunflower_seed":[
            10
        ]
    },
    
    "relationship": {
        "Tom": 0,
        "Alice": 0
    },

    "Map":{
        "Example": {
            "12 13":{
                "Type": "Land",
              "Info": {
                "CropName": "Potato",
                "LiveDay": "1",
                "MaturationDay": "5",
                "Water": true,
                "Fertilizer": 1
              }
            }    
        }
    }

}